{
    "programa": "Educação em Direitos Humanos",
    "area": "Inclusão social",
    "projeto": "Direitos Sociais",
    "titulo": "Direito à Saúde",
    "autor": [
        "Soraia Silveira Mira de Aquino"
    ],
    "dataPublicacao": "07 de maio de 2020",
    "resumo": "O artigo 196 diz: Saúde é direito de todos. É dever do estado garantir a saúde por meio de políticas sociais e econômicas. O objetivo é reduzir o risco de doença com acesso universal e igualitário às ações de proteção e recuperação.",
    "palavrasChave": "Direitos Humanos. Inclusão. Saúde. Folder.",
    "linkDownload": "./produtos/folder_soraia.pdf"
}